hangman/__init__.py
hangman/hangman.py
VoidHangman-0.1.1.dist-info/METADATA
VoidHangman-0.1.1.dist-info/WHEEL
VoidHangman-0.1.1.dist-info/top_level.txt
VoidHangman-0.1.1.dist-info/RECORD
