Metadata-Version: 2.1
Name: VoidHangman
Version: 0.1.1
Summary: A simple Hangman game module for Discord bots
Home-page: https://github.com/voidfy69/Hangman-Module.git
Author: Void
Author-email: voidfy948@gmail.com
Classifier: Programming Language :: Python :: 3
Classifier: License :: OSI Approved :: MIT License
Classifier: Operating System :: OS Independent
Requires-Python: >=3.6
